clidog/__init__.py
clidog/cli.py
clidog/cli_example.py
clidog/clis/__init__.py
clidog/clis/demo.py
clidog/clis/hdfs.py
clidog/clis/ip.py
clidog/clis/md5.py
clidog/clis/send_mail.py
clidog/clis/sh.py
clidog/clis/spark.py
clidog/clis/spark.yml
clidog-2019.10.17.11.7.42.dist-info/METADATA
clidog-2019.10.17.11.7.42.dist-info/RECORD
clidog-2019.10.17.11.7.42.dist-info/WHEEL
clidog-2019.10.17.11.7.42.dist-info/entry_points.txt
clidog-2019.10.17.11.7.42.dist-info/top_level.txt
