Metadata-Version: 2.1
Name: clidog
Version: 2019.10.17.11.7.42
Summary: description
Home-page: https://github.com/Jie-Yuan/tql-CLI
Author: JieYuan
Author-email: 313303303@qq.com
Maintainer: JieYuan
Maintainer-email: 313303303@qq.com
License: MIT
Keywords: tool wheel,yuanjie,utils
Platform: all
Classifier: Operating System :: OS Independent
Classifier: Intended Audience :: Developers
Classifier: License :: OSI Approved :: MIT License
Classifier: Programming Language :: Python
Classifier: Programming Language :: Python :: Implementation
Requires-Python: >=3.5
Requires-Dist: fire
Requires-Dist: yagmail[all]
Requires-Dist: pyyaml
